pytest_homeassistant.py
pytest_homeassistant/__init__.py
pytest_homeassistant/aiohttp_mock.py
pytest_homeassistant/async_mock.py
pytest_homeassistant/common.py
pytest_homeassistant/conftest.py
pytest_homeassistant/fixtures.py
pytest_homeassistant/plugin.py
pytest_homeassistant-0.1.0.dist-info/LICENSE
pytest_homeassistant-0.1.0.dist-info/METADATA
pytest_homeassistant-0.1.0.dist-info/WHEEL
pytest_homeassistant-0.1.0.dist-info/entry_points.txt
pytest_homeassistant-0.1.0.dist-info/top_level.txt
pytest_homeassistant-0.1.0.dist-info/RECORD
