Metadata-Version: 2.1
Name: pytest-homeassistant
Version: 0.1.0
Summary: A pytest plugin for use with homeassistant custom components.
Home-page: https://github.com/boralyl/pytest-homeassistant
Author: Aaron Godfrey
Maintainer: Aaron Godfrey
License: MIT
Platform: UNKNOWN
Classifier: Development Status :: 4 - Beta
Classifier: Framework :: Pytest
Classifier: Intended Audience :: Developers
Classifier: Topic :: Software Development :: Testing
Classifier: Programming Language :: Python
Classifier: Programming Language :: Python :: 3.6
Classifier: Programming Language :: Python :: 3.7
Classifier: Programming Language :: Python :: 3.8
Classifier: Programming Language :: Python :: Implementation :: CPython
Classifier: Programming Language :: Python :: Implementation :: PyPy
Classifier: Operating System :: OS Independent
Classifier: License :: OSI Approved :: MIT License
Requires-Python: >=3.6, !=3.0.*, !=3.1.*, !=3.2.*, !=3.3.*
Requires-Dist: homeassistant
Requires-Dist: asynctest (==0.13.0)
Requires-Dist: astroid (==2.3.3)
Requires-Dist: mock-open (==1.4.0)
Requires-Dist: pytest-aiohttp (==0.3.0)
Requires-Dist: pytest-timeout (==1.3.4)
Requires-Dist: pytest (==5.4.2)
Requires-Dist: requests-mock (==1.8.0)
Requires-Dist: responses (==0.10.6)
